[
  {
    "slug": "memo-Switches_VNA_software",
    "number": 4,
    "title": "Switches and VNA Software for Automation",
    "date": "2025-10-22T23:27:39.754075+00:00",
    "first_commit_date": "2025-10-18T00:17:00.283363+00:00",
    "authors": [
      "Charlie G. Tolley"
    ],
    "tags": [
      "VNA",
      "Switching",
      "Automation",
      "Software"
    ],
    "pdf": "/pdfs/Switches_VNA_software.pdf",
    "summary": "",
    "kind": "memo"
  },
  {
    "slug": "memo-switch_config_memo",
    "number": 5,
    "title": "Switch Configuration",
    "date": "2025-10-22T23:27:39.756317+00:00",
    "first_commit_date": "2025-10-18T00:17:00.286408+00:00",
    "authors": [
      "Charlie G. Tolley"
    ],
    "tags": [
      "VNA",
      "Hardware",
      "Automation"
    ],
    "pdf": "/pdfs/switch_config_memo.pdf",
    "summary": "",
    "kind": "memo"
  }
]